pytrends_modern/__init__.py
pytrends_modern/browser_config.py
pytrends_modern/browser_config_camoufox.py
pytrends_modern/camoufox_setup.py
pytrends_modern/cli.py
pytrends_modern/config.py
pytrends_modern/exceptions.py
pytrends_modern/proxy_extension.py
pytrends_modern/py.typed
pytrends_modern/request.py
pytrends_modern/request_async.py
pytrends_modern/rss.py
pytrends_modern/scraper.py
pytrends_modern/utils.py
pytrends_modern-0.2.3.dist-info/licenses/LICENSE
pytrends_modern-0.2.3.dist-info/METADATA
pytrends_modern-0.2.3.dist-info/WHEEL
pytrends_modern-0.2.3.dist-info/entry_points.txt
pytrends_modern-0.2.3.dist-info/top_level.txt
pytrends_modern-0.2.3.dist-info/RECORD
