Metadata-Version: 2.4
Name: pytrends-modern
Version: 0.2.3
Summary: Modern Google Trends API - Combining the best of pytrends, with RSS feeds, Selenium scraping, DrissionPage browser automation, and enhanced features
Author: pytrends-modern contributors
License: MIT
Project-URL: Homepage, https://github.com/yiromo/pytrends-modern
Project-URL: Documentation, https://github.com/yiromo/pytrends-modern#readme
Project-URL: Repository, https://github.com/yiromo/pytrends-modern
Project-URL: Issues, https://github.com/yiromo/pytrends-modern/issues
Keywords: google,trends,api,data,scraping,selenium,rss
Classifier: Development Status :: 5 - Production/Stable
Classifier: Intended Audience :: Developers
Classifier: License :: OSI Approved :: MIT License
Classifier: Programming Language :: Python :: 3
Classifier: Programming Language :: Python :: 3.8
Classifier: Programming Language :: Python :: 3.9
Classifier: Programming Language :: Python :: 3.10
Classifier: Programming Language :: Python :: 3.11
Classifier: Programming Language :: Python :: 3.12
Classifier: Topic :: Software Development :: Libraries :: Python Modules
Requires-Python: >=3.8
License-File: LICENSE
Requires-Dist: requests>=2.28.0
Requires-Dist: pandas>=1.5.0
Requires-Dist: lxml>=4.9.0
Provides-Extra: selenium
Requires-Dist: selenium>=4.0.0; extra == "selenium"
Requires-Dist: webdriver-manager>=4.0.0; extra == "selenium"
Provides-Extra: browser
Requires-Dist: camoufox[geoip]>=0.4.11; extra == "browser"
Requires-Dist: browserforge[all]>=1.0.0; extra == "browser"
Provides-Extra: cli
Requires-Dist: click>=8.0.0; extra == "cli"
Requires-Dist: rich>=13.0.0; extra == "cli"
Provides-Extra: export
Requires-Dist: pyarrow>=10.0.0; extra == "export"
Requires-Dist: openpyxl>=3.0.0; extra == "export"
Provides-Extra: dev
Requires-Dist: pytest>=7.0.0; extra == "dev"
Requires-Dist: pytest-cov>=4.0.0; extra == "dev"
Requires-Dist: pytest-vcr>=1.0.2; extra == "dev"
Requires-Dist: black>=23.0.0; extra == "dev"
Requires-Dist: mypy>=1.0.0; extra == "dev"
Requires-Dist: ruff>=0.1.0; extra == "dev"
Provides-Extra: all
Requires-Dist: pytrends-modern[cli,export,selenium]; extra == "all"
Dynamic: license-file
